pyams_auth_http/__init__.py
pyams_auth_http/include.py
pyams_auth_http/plugin.py
pyams_auth_http/doctests/README.rst
pyams_auth_http/locales/pyams_auth_http.pot
pyams_auth_http/locales/fr/LC_MESSAGES/pyams_auth_http.mo
pyams_auth_http/locales/fr/LC_MESSAGES/pyams_auth_http.po
pyams_auth_http/tests/__init__.py
pyams_auth_http/tests/test_utilsdocs.py
pyams_auth_http/tests/test_utilsdocstrings.py
pyams_auth_http-2.0.1.dist-info/LICENSE
pyams_auth_http-2.0.1.dist-info/METADATA
pyams_auth_http-2.0.1.dist-info/WHEEL
pyams_auth_http-2.0.1.dist-info/namespace_packages.txt
pyams_auth_http-2.0.1.dist-info/top_level.txt
pyams_auth_http-2.0.1.dist-info/RECORD
